oceanumlab/__init__.py
oceanumlab/_version.py
oceanumlab/handlers.py
oceanumlab/tests/__init__.py
oceanumlab/tests/test_handlers.py
oceanumlab/tests/test_settings.ipynb
oceanumlab-4.0.3.data/data/etc/jupyter/jupyter_server_config.d/oceanumlab.json
oceanumlab-4.0.3.data/data/share/jupyter/labextensions/@oceanum/oceanumlab/build_log.json
oceanumlab-4.0.3.data/data/share/jupyter/labextensions/@oceanum/oceanumlab/package.json
oceanumlab-4.0.3.data/data/share/jupyter/labextensions/@oceanum/oceanumlab/schemas/@oceanum/oceanumlab/datamesh-connect.json
oceanumlab-4.0.3.data/data/share/jupyter/labextensions/@oceanum/oceanumlab/schemas/@oceanum/oceanumlab/package.json.orig
oceanumlab-4.0.3.data/data/share/jupyter/labextensions/@oceanum/oceanumlab/static/lib_index_js.530628c0357b08f0d8e4.js
oceanumlab-4.0.3.data/data/share/jupyter/labextensions/@oceanum/oceanumlab/static/lib_index_js.530628c0357b08f0d8e4.js.map
oceanumlab-4.0.3.data/data/share/jupyter/labextensions/@oceanum/oceanumlab/static/remoteEntry.84ea3016bc7ebdacc5dd.js
oceanumlab-4.0.3.data/data/share/jupyter/labextensions/@oceanum/oceanumlab/static/remoteEntry.84ea3016bc7ebdacc5dd.js.map
oceanumlab-4.0.3.data/data/share/jupyter/labextensions/@oceanum/oceanumlab/static/style.js
oceanumlab-4.0.3.data/data/share/jupyter/labextensions/@oceanum/oceanumlab/static/style_index_js.089f3d25ce6bfdcec72d.js
oceanumlab-4.0.3.data/data/share/jupyter/labextensions/@oceanum/oceanumlab/static/style_index_js.089f3d25ce6bfdcec72d.js.map
oceanumlab-4.0.3.data/data/share/jupyter/labextensions/@oceanum/oceanumlab/static/vendors-node_modules_phosphor-icons_react_dist_index_mjs.d28fe157162aff53d727.js
oceanumlab-4.0.3.data/data/share/jupyter/labextensions/@oceanum/oceanumlab/static/vendors-node_modules_phosphor-icons_react_dist_index_mjs.d28fe157162aff53d727.js.map
oceanumlab-4.0.3.data/data/share/jupyter/labextensions/@oceanum/oceanumlab/install.json
oceanumlab-4.0.3.dist-info/METADATA
oceanumlab-4.0.3.dist-info/WHEEL
oceanumlab-4.0.3.dist-info/licenses/LICENSE
oceanumlab-4.0.3.dist-info/RECORD
