Metadata-Version: 2.3
Name: oceanumlab
Version: 4.0.3
Dynamic: Keywords
Summary: A Jupyterlab extension to interact with the Oceanum.io platform
Project-URL: Homepage, https://github.com/oceanum-io/oceanumlab.git
Project-URL: Bug Tracker, https://github.com/oceanum-io/oceanumlab.git/issues
Project-URL: Repository, https://github.com/oceanum-io/oceanumlab.git
Author-email: Oceanum <developers@oceanum.science>
License: BSD 3-Clause License
License-File: LICENSE
Classifier: Framework :: Jupyter
Classifier: Framework :: Jupyter :: JupyterLab
Classifier: Framework :: Jupyter :: JupyterLab :: 4
Classifier: Framework :: Jupyter :: JupyterLab :: Extensions
Classifier: Framework :: Jupyter :: JupyterLab :: Extensions :: Prebuilt
Classifier: License :: OSI Approved :: BSD License
Classifier: Programming Language :: Python
Classifier: Programming Language :: Python :: 3
Classifier: Programming Language :: Python :: 3.10
Classifier: Programming Language :: Python :: 3.11
Classifier: Programming Language :: Python :: 3.12
Requires-Python: >=3.10
Requires-Dist: jupyter-server<3,>=2.0.1
Provides-Extra: test
Requires-Dist: coverage; extra == 'test'
Requires-Dist: pytest; extra == 'test'
Requires-Dist: pytest-asyncio; extra == 'test'
Requires-Dist: pytest-cov; extra == 'test'
Requires-Dist: pytest-jupyter[server]>=0.6.0; extra == 'test'
